{
  "name": "TATA CHEMICALS",
  "price history": {
    "price": ["Rs", "", "%ch", "%", ""],
    "Mkt Cap": ["Rs m", "192,710", "No. of shares", "m", "245.76"],
    "Vol": ["'000", "120.4", "%ch week", "%", "-1.1"],
    "P/E": ["X", "46.9", "%ch 1-mth", "%", "2.7"],
    "P/CF": ["X", "16.5", "%ch 12-mth", "%", "153.6"],
    "EPS(TTM)": ["Rs", "16.1", "52 week H/L", "Rs", "834.0/273.6"]
  },
  "equity share data": {
    "High":                         ["Rs", ""],
    "Low":                          ["Rs", ""],
    "Sales per share(Unadj.)":      ["Rs", ""],
    "Earnings per Share(Unadj.)":   ["Rs", ""],
    "Diluted earnings per share":   ["Rs", ""],
    "Cash flow per share(Unadj.)":  ["Rs", ""],
    "Dividents per share(Unadj.)":  ["Rs", ""],
    "Adj. dividents per share":     ["Rs", ""],
    "Divident yield(eoy)":          ["Rs", ""],
    "Book value per share(Unadj.)": ["Rs", ""],
    "Adj. book value per share":    ["Rs", ""],
    "Shares outstanding(eoy)":      ["Rs", ""],
    "Price/ Sales ratio":           ["Rs", ""],
    "Average P/E ratio":            ["Rs", ""],
    "P/CF ratio(eoy)":              ["Rs", ""],
    "Price/ Book Value ratio":      ["Rs", ""],
    "Divident Payout":              ["Rs", ""],
    "Avg Market Cap":               ["Rs", ""],
    "Total wages/salary":           ["Rs", ""]
  },
  "income data": {
    "Net Sales":                ["Rs m", ""],
    "Other Income":             ["Rs m", ""],
    "Total revenue":            ["Rs m", ""],
    "Gross Profit":             ["Rs m", ""],
    "Depreciation":             ["Rs m", ""],
    "Intrest":                  ["Rs m", ""],
    "Profit Before Tax":        ["Rs m", ""],
    "Minority Intrest":         ["Rs m", ""],
    "Prior Period Items":       ["Rs m", ""],
    "Extraordinary Inc (Exp)":  ["Rs m", ""],
    "tax":                      ["Rs m", ""],
    "Profit After Tax":         ["Rs m", ""],
    "Gross Profit Margin":      ["Rs m", ""],
    "Effective tax rate":       ["Rs m", ""],
    "Net Profit Margin":        ["Rs m", ""]
  },
  "balance sheet data": {
    "Current Assets":             ["Rs m", ""],
    "Current Liabilities":        ["Rs m", ""],
    "Net working cap to sales":   ["Rs m", ""],
    "Current ratio":              ["Rs m", ""],
    "Inventory Days":             ["Rs m", ""],
    "Debtors Days":               ["Rs m", ""],
    "Net Fixed assets":           ["Rs m", ""],
    "Share Capital":              ["Rs m", ""],
    "FREE reserves":              ["Rs m", ""],
    "Net Worth":                  ["Rs m", ""],
    "Long term debt":             ["Rs m", ""],
    "Total assets":               ["Rs m", ""],
    "Intrest Coverage":           ["Rs m", ""],
    "Debt to equity ratio":       ["Rs m", ""],
    "Sales to assets ratio":      ["Rs m", ""],
    "Return on assets":           ["Rs m", ""],
    "Return on equity":           ["Rs m", ""],
    "Return on Capital":          ["Rs m", ""],
    "Exports to sales":           ["Rs m", ""],
    "Import to sales":            ["Rs m", ""],
    "Exports(fob)":               ["Rs m", ""],
    "Imports(cif)":               ["Rs m", ""],
    "Fx inflow":                  ["Rs m", ""],
    "Fx outflow":                 ["Rs m", ""],
    "Net fx":                     ["Rs m", ""]
  },
  "cash flow": {
    "From Operations":          ["Rs m", ""],
    "From Investers":           ["Rs m", ""],
    "From Finincial Activity":  ["Rs m", ""],
    "Net Cashflow":             ["Rs m", ""]
  },
  "share holding": {
    "Indian Promoters": "38.0%",
    "Foreign Colaborators": "0.0%",
    "Indian inst/Mut Fund": "34.8%",
    "Flls":"14.0%",
    "ADR/GDR": "0.0%",
    "Free float": "62.0%",
    "Share Holders": "398,693",
    "Pledged promoter(s) holding": "0.0%"
  },
  "company information": {
    "REGD Off": "",
    "E-mail": "",
    "WEB": "",
    "Tel": "",
    "FAX": "",
    "SECTOR": "",
    "GROUP": "",
    "TR AGENT": "",
    "AUDITOR": ""
  }
}